sealant/__init__.py
sealant/cdp.py
sealant/config.py
sealant/errors.py
sealant/heapfile_processing.py
sealant/logger.py
sealant/sealant_decorator.py
SeaLant-1.0.2.dist-info/LICENSE.md
SeaLant-1.0.2.dist-info/METADATA
SeaLant-1.0.2.dist-info/WHEEL
SeaLant-1.0.2.dist-info/top_level.txt
SeaLant-1.0.2.dist-info/RECORD
